{"TextId":1658,"Content":"Remember days of yesterday, how it flew so fast. The two score and a year we had, I thought it would always last. Those summer days and west coast dreams, I wished would never end. A young boy and his father, idol, and best friend. I'll always remember - those were the best of times. A lifetime together, I'll never forget. The morning shows on the radio, the case of the missing dog.","Source":"The Best of Times","Author":"Dream Theater","Contributor":"Vielle#4742","Locale":"en","Enabled":1,"StarRating":7.2872925,"Obscurity":4.7927837,"Density":4.318269,"LengthR":6.067753}