{"TextId":2190,"Content":"I waited and waited to see you all come down the sidewalk, and as I waited I thought, Atticus Finch won't win, he can't win, but he's the only man in these parts who can keep a jury out so long in a case like that. And I thought to myself, well, we're taking a step - it's just a baby-step, but it's a step.","Source":"To Kill a Mockingbird","Author":"Harper Lee","Contributor":"Unknown","Locale":"en","Enabled":1,"StarRating":6.617094,"Obscurity":4.198847,"Density":4.581489,"LengthR":5.361894}