{"TextId":2380,"Content":"\"Send me your hungry, old Earth. Here's Sam Parkhill, his hot dogs all boiled, his chili cooking, everything neat as a pin. Come on, you Earth, send me your rocket!\" \"It sure makes you humble,\" he said among the cooking odors of wieners, warm buns, rich butter. \"Step up,\" he invited the various stars in the sky. \"Who'll be the first to buy?\"","Source":"The Martian Chronicles","Author":"Ray Bradbury","Contributor":"Unknown","Locale":"en","Enabled":1,"StarRating":10.142792,"Obscurity":6.9333496,"Density":8.750434,"LengthR":5.71504}