{"TextId":446,"Content":"Cynicism is the only form in which base souls approach what is called honesty; and the higher man must open his ears to all the coarser or finer cynicism, and congratulate himself when the clown becomes shameless right before him, or the scientific satyr speaks out.","Source":"Beyond Good and Evil","Author":"Friedrich Wilhelm Nietzsche","Contributor":"Fruit#7132","Locale":"en","Enabled":1,"StarRating":6.3621755,"Obscurity":6.3877125,"Density":2.6692424,"LengthR":4.8927627}