{"_id":"BJMyCNKXdG6EDvGFR","textId":1068,"content":"Achilles (a Greek warrior, the fleetest of foot of all mortals) and a Tortoise are standing together on a dusty runway in the hot sun. Far down the runway, on a tall flagpole, there hangs a large rectangular flag. The flag is solid red, except where a thin ring-shaped hole has been cut out of it, through which one can see the sky.","author":"Douglas R. Hoftstadter","source":"Godel, Escher, Bach: an Eternal Golden Braid","contributor":"cody#9609","locale":"en","enabled":1,"created":1612768473}