{"_id":"622e31b3e9a21a5c656e635b","textId":2192,"content":"I'm guessin' that if we can make some wishes out of airplanes, then maybe, oh maybe, I'll go back to the days before the politics that we call the rap game, and back when ain't nobody listened to my mixtape. So can I get a wish to end the politics, and get back to the music that started this...? So here I stand, and then again I say - I'm hoping we can make some wishes out of airplanes.","source":"Airplanes (ft. Haley Williams)","author":"B.o.B","contributor":"Unknown","locale":"en","enabled":1,"created":"1646430843"}