{"_id":"622e31b3e9a21a5c656e636c","textId":2209,"content":"A wizard of Oz prototype fakes functionality that you want to test with users, saving you the time and money of actually creating it. Wizard of Oz prototypes often refer to prototypes of digital systems, in which the user thinks the response is computer-driven, when in fact it's human-controlled.","source":"Design Thinking Bootleg","author":"Institue of Design at Stanford","contributor":"Unknown","locale":"en","enabled":1,"created":"1646430843"}